cafeplotter/__init__.py
cafeplotter/cafeparser.py
cafeplotter/scripts/__init__.py
cafeplotter/scripts/cafeplotter.py
cafeplotter/treeplotter.py
cafeplotter-0.2.0.dist-info/LICENSE
cafeplotter-0.2.0.dist-info/METADATA
cafeplotter-0.2.0.dist-info/WHEEL
cafeplotter-0.2.0.dist-info/entry_points.txt
cafeplotter-0.2.0.dist-info/RECORD
