Metadata-Version: 2.1
Name: cafeplotter
Version: 0.2.0
Summary: A tool for plotting CAFE5 gene family expansion/contraction result
Home-page: https://github.com/moshi4/CafePlotter/
License: MIT
Keywords: bioinformatics,phylogenetics,molecular-evolution,visualization,matplotlib
Author: moshi4
Requires-Python: >=3.8.1
Classifier: Framework :: Matplotlib
Classifier: Intended Audience :: Science/Research
Classifier: License :: OSI Approved :: MIT License
Classifier: Programming Language :: Python :: 3
Classifier: Programming Language :: Python :: 3.9
Classifier: Programming Language :: Python :: 3.10
Classifier: Programming Language :: Python :: 3.11
Classifier: Topic :: Scientific/Engineering :: Bio-Informatics
Requires-Dist: biopython (>=1.80)
Requires-Dist: matplotlib (>=3.5.3)
Requires-Dist: numpy (>=1.21.1)
Project-URL: Repository, https://github.com/moshi4/CafePlotter/
